ggen/__init__.py
ggen/driver_mod.py
ggen/gen_exodus.py
ggen/gen_phys_grids.py
ggen/gen_rll_grid.py
ggen/gen_scrip_file.py
ggen/get_face_area.py
ggen/ggrids.py
ggen/main.py
ggen/utils.py
ggen-1.1.0.dist-info/LICENSE
ggen-1.1.0.dist-info/METADATA
ggen-1.1.0.dist-info/WHEEL
ggen-1.1.0.dist-info/entry_points.txt
ggen-1.1.0.dist-info/top_level.txt
ggen-1.1.0.dist-info/RECORD
