Metadata-Version: 2.1
Name: ggen
Version: 1.1.0
Summary: Package for generating grid meshes and performing conservative remapping
Home-page: https://github.com/TaufiqHassan/ggen
Author: Taufiq Hassan
Author-email: taufiq.hassan@pnnl.gov
License: MIT
Classifier: License :: OSI Approved :: MIT License
Classifier: Natural Language :: English
Classifier: Programming Language :: Python :: 3.7
License-File: LICENSE
Requires-Dist: xarray
Requires-Dist: pandas
Requires-Dist: setuptools
Requires-Dist: scipy
Requires-Dist: netCDF4
Requires-Dist: nco
Requires-Dist: tempest-remap
